aethermagic/__init__.py
aethermagic/magic.py
aethermagic/task.py
aethermagic/protocols/__init__.py
aethermagic/protocols/mqtt_protocol.py
aethermagic/protocols/redis_protocol.py
aethermagic/protocols/redis_protocol_backup.py
aethermagic/protocols/redis_protocol_simple.py
aethermagic/protocols/websocket_protocol.py
aethermagic/protocols/zeromq_protocol.py
aethermagic-0.2.23.dist-info/METADATA
aethermagic-0.2.23.dist-info/WHEEL
aethermagic-0.2.23.dist-info/licenses/LICENSE
aethermagic-0.2.23.dist-info/RECORD
