Metadata-Version: 2.4
Name: aethermagic
Version: 0.2.23
Summary: AetherMagic - Multi-protocol communications library with channel support (MQTT, Redis, WebSocket, ZeroMQ, RabbitMQ)
Project-URL: Homepage, https://github.com/www-oto-dev/aether-magic
Project-URL: Issues, https://github.com/www-oto-dev/aether/issues
Author-email: Michael Galizki <michael@galizki.com>
License-File: LICENSE
Classifier: License :: OSI Approved :: MIT License
Classifier: Operating System :: OS Independent
Classifier: Programming Language :: Python :: 3
Requires-Python: >=3.8
Requires-Dist: asgiref>=3.8.1
Requires-Dist: asyncio
Requires-Dist: certifi
Provides-Extra: all
Requires-Dist: aio-pika>=8.0.0; extra == 'all'
Requires-Dist: aiohttp>=3.8.0; extra == 'all'
Requires-Dist: aiomqtt>=2.0.0; extra == 'all'
Requires-Dist: paho-mqtt>=2.1.0; extra == 'all'
Requires-Dist: pyzmq>=24.0.0; extra == 'all'
Requires-Dist: redis[hiredis]>=4.0.0; extra == 'all'
Requires-Dist: websockets>=10.0; extra == 'all'
Provides-Extra: mqtt
Requires-Dist: aiomqtt>=2.0.0; extra == 'mqtt'
Requires-Dist: paho-mqtt>=1.6.0; extra == 'mqtt'
Provides-Extra: rabbitmq
Requires-Dist: aio-pika>=8.0.0; extra == 'rabbitmq'
Provides-Extra: redis
Requires-Dist: redis[hiredis]>=4.0.0; extra == 'redis'
Provides-Extra: websocket
Requires-Dist: aiohttp>=3.8.0; extra == 'websocket'
Requires-Dist: websockets>=10.0; extra == 'websocket'
Provides-Extra: zeromq
Requires-Dist: pyzmq>=24.0.0; extra == 'zeromq'
